datacrane/__init__.py
datacrane-0.0.1.dist-info/WHEEL
datacrane-0.0.1.dist-info/METADATA
datacrane-0.0.1.dist-info/RECORD
