Metadata-Version: 2.1
Name: datacrane
Version: 0.0.1
Summary: Lift your data out of the bog
Author-email: Gil Forsyth <gil@forsyth.dev>
